SupetDazaoGongshengXingGongyeHulianwangPingtaiShengtaiBaipishuFix1/README.md
SupetDazaoGongshengXingGongyeHulianwangPingtaiShengtaiBaipishuFix1/__init__.py
SupetDazaoGongshengXingGongyeHulianwangPingtaiShengtaiBaipishuFix1/__main__.py
SupetDazaoGongshengXingGongyeHulianwangPingtaiShengtaiBaipishuFix1/file.pdf
SupetDazaoGongshengXingGongyeHulianwangPingtaiShengtaiBaipishuFix1/index.html
supet_dazao_gongsheng_xing_gongye_hulianwang_pingtai_shengtai_baipishu_fix1-2025.3.25.1.dist-info/METADATA
supet_dazao_gongsheng_xing_gongye_hulianwang_pingtai_shengtai_baipishu_fix1-2025.3.25.1.dist-info/WHEEL
supet_dazao_gongsheng_xing_gongye_hulianwang_pingtai_shengtai_baipishu_fix1-2025.3.25.1.dist-info/entry_points.txt
supet_dazao_gongsheng_xing_gongye_hulianwang_pingtai_shengtai_baipishu_fix1-2025.3.25.1.dist-info/top_level.txt
supet_dazao_gongsheng_xing_gongye_hulianwang_pingtai_shengtai_baipishu_fix1-2025.3.25.1.dist-info/RECORD
